<?xml version="1.0" encoding='windows-1250'?>
<!DOCTYPE ViewObject SYSTEM "jbo_03_01.dtd">

<ViewObject
   Name="VwKpSpolecnostzamekgendatumView"
   SelectList="VwKpSpolecnostzamekgendatum.DT_DATUM"
   FromList="DB_JT.VW_KP_SPOLECNOSTZAMEKGENDATUM VwKpSpolecnostzamekgendatum"
   BindingStyle="Oracle"
   CustomQuery="false"
   ComponentClass="cz.jtbank.konsolidace.doklady.VwKpSpolecnostzamekgendatumViewImpl"
   MsgBundleClass="oracle.jbo.common.JboResourceBundle"
   UseGlueCode="false" >
   <DesignTime>
      <Attr Name="_version" Value="9.0.4.13.65" />
      <Attr Name="_CodeGenFlagNew" Value="36" />
   </DesignTime>
   <EntityUsage
      Name="VwKpSpolecnostzamekgendatum"
      Entity="cz.jtbank.konsolidace.doklady.VwKpSpolecnostzamekgendatum" >
      <DesignTime>
         <Attr Name="_EntireObjectTable" Value="false" />
         <Attr Name="_queryClause" Value="false" />
      </DesignTime>
   </EntityUsage>
   <ViewAttribute
      Name="DtDatum"
      IsNotNull="true"
      EntityAttrName="DtDatum"
      EntityUsage="VwKpSpolecnostzamekgendatum"
      AliasName="DT_DATUM"
      ColumnType="VARCHAR2" >
   </ViewAttribute>
</ViewObject>
